src/vtim/vtim.v
/////////////////////////////////////////////////////////////////////
////                                                             ////
////  WISHBONE rev.B2 compliant VGA/LCD Core; Timing Generator   ////
////  Video Timing Generator                                     ////
////                                                             ////
////  Author: Richard Herveille                                  ////
////          richard@asics.ws                                   ////
////          www.asics.ws                                       ////
////                                                             ////
////  Downloaded from: http://www.opencores.org/projects/vga_lcd ////
////                                                             ////
/////////////////////////////////////////////////////////////////////
////                                                             ////
//// Copyright (C) 2001 Richard Herveille                        ////
////                    richard@asics.ws                         ////
////                                                             ////
//// This source file may be used and distributed without        ////
//// restriction provided that this copyright statement is not   ////
//// removed from the file and that any derivative work contains ////
//// the original copyright notice and the associated disclaimer.////
////                                                             ////
////     THIS SOFTWARE IS PROVIDED ``AS IS'' AND WITHOUT ANY     ////
//// EXPRESS OR IMPLIED WARRANTIES, INCLUDING, BUT NOT LIMITED   ////
//// TO, THE IMPLIED WARRANTIES OF MERCHANTABILITY AND FITNESS   ////
//// FOR A PARTICULAR PURPOSE. IN NO EVENT SHALL THE AUTHOR      ////
//// OR CONTRIBUTORS BE LIABLE FOR ANY DIRECT, INDIRECT,         ////
//// INCIDENTAL, SPECIAL, EXEMPLARY, OR CONSEQUENTIAL DAMAGES    ////
//// (INCLUDING, BUT NOT LIMITED TO, PROCUREMENT OF SUBSTITUTE   ////
//// GOODS OR SERVICES; LOSS OF USE, DATA, OR PROFITS; OR        ////
//// BUSINESS INTERRUPTION) HOWEVER CAUSED AND ON ANY THEORY OF  ////
//// LIABILITY, WHETHER IN  CONTRACT, STRICT LIABILITY, OR TORT  ////
//// (INCLUDING NEGLIGENCE OR OTHERWISE) ARISING IN ANY WAY OUT  ////
//// OF THE USE OF THIS SOFTWARE, EVEN IF ADVISED OF THE         ////
//// POSSIBILITY OF SUCH DAMAGE.                                 ////
////                                                             ////
/////////////////////////////////////////////////////////////////////

//  CVS Log
//
//  $Id: vga_vtim.v,v 1.8 2003/05/07 09:48:54 rherveille Exp $
//
//  $Date: 2003/05/07 09:48:54 $
//  $Revision: 1.8 $
//  $Author: rherveille $
//  $Locker:  $
//  $State: Exp $
//
// Change History:
//               $Log: vga_vtim.v,v $
//               Revision 1.8  2003/05/07 09:48:54  rherveille
//               Fixed some Wishbone RevB.3 related bugs.
//               Changed layout of the core. Blocks are located more logically now.
//               Started work on a dual clocked/double edge 12bit output. Commonly used by external devices like DVI transmitters.
//
//               Revision 1.7  2003/03/19 12:50:45  rherveille
//               Changed timing generator; made it smaller and easier.
//
//               Revision 1.6  2002/04/20 10:02:39  rherveille
//               Changed video timing generator.
//               Changed wishbone master vertical gate count code.
//               Fixed a potential bug in the wishbone slave (cursor color register readout).
//
//               Revision 1.5  2002/01/28 03:47:16  rherveille
//               Changed counter-library.
//               Changed vga-core.
//               Added 32bpp mode.
//



`timescale 1 ns / 1 ns


module vga_vtim(clk, ena, rst, Tsync, Tgdel, Tgate, Tlen, Sync, Gate, Done);
	// inputs & outputs
	input clk; // master clock
	input ena; // count enable
	input rst; // synchronous active high reset

	input [ 7:0] Tsync; // sync duration
	input [ 7:0] Tgdel; // gate delay
	input [15:0] Tgate; // gate length
	input [15:0] Tlen;  // line time / frame time

	output Sync; // synchronization pulse
	output Gate; // gate
	output Done; // done with line/frame
	reg Sync;
	reg Gate;
	reg Done;

	//
	// module body
	//

	// generate timing statemachine
	reg  [15:0] cnt, cnt_len;
	wire [16:0] cnt_nxt, cnt_len_nxt;
	wire        cnt_done, cnt_len_done;

	assign cnt_nxt = {1'b0, cnt} -17'h1;
	assign cnt_done = cnt_nxt[16];

	assign cnt_len_nxt = {1'b0, cnt_len} -17'h1;
	assign cnt_len_done = cnt_len_nxt[16];

	reg [4:0] state;
	parameter [4:0] idle_state = 5'b00001;
	parameter [4:0] sync_state = 5'b00010;
	parameter [4:0] gdel_state = 5'b00100;
	parameter [4:0] gate_state = 5'b01000;
	parameter [4:0] len_state  = 5'b10000;

	always @(posedge clk)
	  if (rst)
	    begin
	        state   <= #1 idle_state;
	        cnt     <= #1 16'h0;
	        cnt_len <= #1 16'b0;
	        Sync    <= #1 1'b0;
	        Gate    <= #1 1'b0;
	        Done    <= #1 1'b0;
	    end
	  else if (ena)
	    begin
	        cnt     <= #1 cnt_nxt[15:0];
	        cnt_len <= #1 cnt_len_nxt[15:0];

	        Done    <= #1 1'b0;

	        case (state) // synopsys full_case parallel_case
	          idle_state:
	            begin
	                state   <= #1 sync_state;
	                cnt     <= #1 Tsync;
	                cnt_len <= #1 Tlen;

	                Sync    <= #1 1'b1;
	            end

	          sync_state:
	            if (cnt_done)
	              begin
	                  state <= #1 gdel_state;
	                  cnt   <= #1 Tgdel;

	                  Sync  <= #1 1'b0;
	              end

	          gdel_state:
	            if (cnt_done)
	              begin
	                  state <= #1 gate_state;
	                  cnt   <= #1 Tgate;

	                  Gate  <= #1 1'b1;
	              end

	          gate_state:
	            if (cnt_done)
	              begin
	                  state <= #1 len_state;

	                  Gate  <= #1 1'b0;
	              end

	          len_state:
	            if (cnt_len_done)
	              begin
	                  state   <= #1 sync_state;
	                  cnt     <= #1 Tsync;
	                  cnt_len <= #1 Tlen;

	                  Sync    <= #1 1'b1;
	                  Done    <= #1 1'b1;
	              end

	        endcase
	    end
endmodule

src/vtim/sim_vtim.v

`timescale 1 ns / 1 ns

module sim_i2c();


	reg clk; // master clock
	reg ena; // count enable
	reg rst; // synchronous active high reset

	reg [ 7:0] Tsync = 4; // sync duration
	reg [ 7:0] Tgdel = 5; // gate delay
	reg [15:0] Tgate = 6; // gate length
	reg [15:0] Tlen  = 7;  // line time / frame time

	wire Sync; // synchronization pulse
	wire Gate; // gate
	wire Done; // done with line/frame
	
	vga_vtim vtim (clk, ena, rst, Tsync, Tgdel, Tgate, Tlen, Sync, Gate, Done);

	initial begin
	
		$dumpfile("vtim.vcd");
		$dumpvars(1, vtim);
		
		clk <= 0;
		rst <= 0;
		ena <= 1;
		
		#3 rst <= 1;
		#3 rst <= 0;
		
	end
	
	always #1 clk = ~clk;
	always #1000 $finish;
	

endmodule

src/vtim/vtim.vcd
$date
    Thu Aug 11 08:54:50 2005
$end
$version
    GPLCVER_2.10c of 02/28/05
$end
$timescale
    1 ps
$end
$scope module sim_i2c $end
$scope module vtim $end
$var reg       1 !    Done $end
$var reg       1 "    Gate $end
$var reg       1 #    Sync $end
$var wire      16 $    Tgate [15:0] $end
$var wire       8 %    Tgdel [7:0] $end
$var wire      16 &    Tlen [15:0] $end
$var wire       8 '    Tsync [7:0] $end
$var wire       1 (    clk $end
$var reg      16 )    cnt [15:0] $end
$var wire       1 *    cnt_done $end
$var reg      16 +    cnt_len [15:0] $end
$var wire       1 ,    cnt_len_done $end
$var wire      17 -    cnt_len_nxt [16:0] $end
$var wire      17 .    cnt_nxt [16:0] $end
$var wire       1 /    ena $end
$var wire       1 0    rst $end
$var reg       5 1    state [4:0] $end
$upscope $end
$upscope $end
$enddefinitions $end
#0
$dumpvars
x!
x"
x#
b110 $
b101 %
b111 &
b100 '
0(
bx )
x*
bx +
x,
bx -
bx .
1/
00
bx 1
$end
#1000
1(
#2000
0!
0(
#3000
10
1(
#4000
0(
#5000
1(
#6000
1,
1*
b11111111111111111 -
b11111111111111111 .
00
0"
0#
b0 +
b0 )
b1 1
0(
#7000
1(
#8000
0,
0*
b110 -
b11 .
1#
b10 1
b111 +
b100 )
0(
#9000
1(
#10000
b101 -
b10 .
b110 +
b11 )
0(
#11000
1(
#12000
b100 -
b1 .
b101 +
b10 )
0(
#13000
1(
#14000
b11 -
b0 .
b100 +
b1 )
0(
#15000
1(
#16000
1*
b10 -
b11111111111111111 .
b11 +
b0 )
0(
#17000
1(
#18000
0*
b1 -
b100 .
0#
b100 1
b10 +
b101 )
0(
#19000
1(
#20000
b0 -
b11 .
b1 +
b100 )
0(
#21000
1(
#22000
1,
b11111111111111111 -
b10 .
b0 +
b11 )
0(
#23000
1(
#24000
0,
b1111111111111110 -
b1 .
b1111111111111111 +
b10 )
0(
#25000
1(
#26000
b1111111111111101 -
b0 .
b1111111111111110 +
b1 )
0(
#27000
1(
#28000
1*
b1111111111111100 -
b11111111111111111 .
b1111111111111101 +
b0 )
0(
#29000
1(
#30000
0*
b1111111111111011 -
b101 .
1"
b1000 1
b1111111111111100 +
b110 )
0(
#31000
1(
#32000
b1111111111111010 -
b100 .
b1111111111111011 +
b101 )
0(
#33000
1(
#34000
b1111111111111001 -
b11 .
b1111111111111010 +
b100 )
0(
#35000
1(
#36000
b1111111111111000 -
b10 .
b1111111111111001 +
b11 )
0(
#37000
1(
#38000
b1111111111110111 -
b1 .
b1111111111111000 +
b10 )
0(
#39000
1(
#40000
b1111111111110110 -
b0 .
b1111111111110111 +
b1 )
0(
#41000
1(
#42000
1*
b1111111111110101 -
b11111111111111111 .
b1111111111110110 +
b0 )
0(
#43000
1(
#44000
0*
b1111111111110100 -
b1111111111111110 .
0"
b10000 1
b1111111111110101 +
b1111111111111111 )
0(
#45000
1(
#46000
b1111111111110011 -
b1111111111111101 .
b1111111111110100 +
b1111111111111110 )
0(
#47000
1(
#48000
b1111111111110010 -
b1111111111111100 .
b1111111111110011 +
b1111111111111101 )
0(
#49000
1(
#50000
b1111111111110001 -
b1111111111111011 .
b1111111111110010 +
b1111111111111100 )
0(
#51000
1(
#52000
b1111111111110000 -
b1111111111111010 .
b1111111111110001 +
b1111111111111011 )
0(
#53000
1(
#54000
b1111111111101111 -
b1111111111111001 .
b1111111111110000 +
b1111111111111010 )
0(
#55000
1(
#56000
b1111111111101110 -
b1111111111111000 .
b1111111111101111 +
b1111111111111001 )
0(
#57000
1(
#58000
b1111111111101101 -
b1111111111110111 .
b1111111111101110 +
b1111111111111000 )
0(
#59000
1(
#60000
b1111111111101100 -
b1111111111110110 .
b1111111111101101 +
b1111111111110111 )
0(
#61000
1(
#62000
b1111111111101011 -
b1111111111110101 .
b1111111111101100 +
b1111111111110110 )
0(
#63000
1(
#64000
b1111111111101010 -
b1111111111110100 .
b1111111111101011 +
b1111111111110101 )
0(
#65000
1(
#66000
b1111111111101001 -
b1111111111110011 .
b1111111111101010 +
b1111111111110100 )
0(
#67000
1(
#68000
b1111111111101000 -
b1111111111110010 .
b1111111111101001 +
b1111111111110011 )
0(
#69000
1(
#70000
b1111111111100111 -
b1111111111110001 .
b1111111111101000 +
b1111111111110010 )
0(
#71000
1(
#72000
b1111111111100110 -
b1111111111110000 .
b1111111111100111 +
b1111111111110001 )
0(
#73000
1(
#74000
b1111111111100101 -
b1111111111101111 .
b1111111111100110 +
b1111111111110000 )
0(
#75000
1(
#76000
b1111111111100100 -
b1111111111101110 .
b1111111111100101 +
b1111111111101111 )
0(
#77000
1(
#78000
b1111111111100011 -
b1111111111101101 .
b1111111111100100 +
b1111111111101110 )
0(
#79000
1(
#80000
b1111111111100010 -
b1111111111101100 .
b1111111111100011 +
b1111111111101101 )
0(
#81000
1(
#82000
b1111111111100001 -
b1111111111101011 .
b1111111111100010 +
b1111111111101100 )
0(
#83000
1(
#84000
b1111111111100000 -
b1111111111101010 .
b1111111111100001 +
b1111111111101011 )
0(
#85000
1(
#86000
b1111111111011111 -
b1111111111101001 .
b1111111111100000 +
b1111111111101010 )
0(
#87000
1(
#88000
b1111111111011110 -
b1111111111101000 .
b1111111111011111 +
b1111111111101001 )
0(
#89000
1(
#90000
b1111111111011101 -
b1111111111100111 .
b1111111111011110 +
b1111111111101000 )
0(
#91000
1(
#92000
b1111111111011100 -
b1111111111100110 .
b1111111111011101 +
b1111111111100111 )
0(
#93000
1(
#94000
b1111111111011011 -
b1111111111100101 .
b1111111111011100 +
b1111111111100110 )
0(
#95000
1(
#96000
b1111111111011010 -
b1111111111100100 .
b1111111111011011 +
b1111111111100101 )
0(
#97000
1(
#98000
b1111111111011001 -
b1111111111100011 .
b1111111111011010 +
b1111111111100100 )
0(
#99000
1(
#100000
b1111111111011000 -
b1111111111100010 .
b1111111111011001 +
b1111111111100011 )
0(
#101000
1(
#102000
b1111111111010111 -
b1111111111100001 .
b1111111111011000 +
b1111111111100010 )
0(
#103000
1(
#104000
b1111111111010110 -
b1111111111100000 .
b1111111111010111 +
b1111111111100001 )
0(
#105000
1(
#106000
b1111111111010101 -
b1111111111011111 .
b1111111111010110 +
b1111111111100000 )
0(
#107000
1(
#108000
b1111111111010100 -
b1111111111011110 .
b1111111111010101 +
b1111111111011111 )
0(
#109000
1(
#110000
b1111111111010011 -
b1111111111011101 .
b1111111111010100 +
b1111111111011110 )
0(
#111000
1(
#112000
b1111111111010010 -
b1111111111011100 .
b1111111111010011 +
b1111111111011101 )
0(
#113000
1(
#114000
b1111111111010001 -
b1111111111011011 .
b1111111111010010 +
b1111111111011100 )
0(
#115000
1(
#116000
b1111111111010000 -
b1111111111011010 .
b1111111111010001 +
b1111111111011011 )
0(
#117000
1(
#118000
b1111111111001111 -
b1111111111011001 .
b1111111111010000 +
b1111111111011010 )
0(
#119000
1(
#120000
b1111111111001110 -
b1111111111011000 .
b1111111111001111 +
b1111111111011001 )
0(
#121000
1(
#122000
b1111111111001101 -
b1111111111010111 .
b1111111111001110 +
b1111111111011000 )
0(
#123000
1(
#124000
b1111111111001100 -
b1111111111010110 .
b1111111111001101 +
b1111111111010111 )
0(
#125000
1(
#126000
b1111111111001011 -
b1111111111010101 .
b1111111111001100 +
b1111111111010110 )
0(
#127000
1(
#128000
b1111111111001010 -
b1111111111010100 .
b1111111111001011 +
b1111111111010101 )
0(
#129000
1(
#130000
b1111111111001001 -
b1111111111010011 .
b1111111111001010 +
b1111111111010100 )
0(
#131000
1(
#132000
b1111111111001000 -
b1111111111010010 .
b1111111111001001 +
b1111111111010011 )
0(
#133000
1(
#134000
b1111111111000111 -
b1111111111010001 .
b1111111111001000 +
b1111111111010010 )
0(
#135000
1(
#136000
b1111111111000110 -
b1111111111010000 .
b1111111111000111 +
b1111111111010001 )
0(
#137000
1(
#138000
b1111111111000101 -
b1111111111001111 .
b1111111111000110 +
b1111111111010000 )
0(
#139000
1(
#140000
b1111111111000100 -
b1111111111001110 .
b1111111111000101 +
b1111111111001111 )
0(
#141000
1(
#142000
b1111111111000011 -
b1111111111001101 .
b1111111111000100 +
b1111111111001110 )
0(
#143000
1(
#144000
b1111111111000010 -
b1111111111001100 .
b1111111111000011 +
b1111111111001101 )
0(
#145000
1(
#146000
b1111111111000001 -
b1111111111001011 .
b1111111111000010 +
b1111111111001100 )
0(
#147000
1(
#148000
b1111111111000000 -
b1111111111001010 .
b1111111111000001 +
b1111111111001011 )
0(
#149000
1(
#150000
b1111111110111111 -
b1111111111001001 .
b1111111111000000 +
b1111111111001010 )
0(
#151000
1(
#152000
b1111111110111110 -
b1111111111001000 .
b1111111110111111 +
b1111111111001001 )
0(
#153000
1(
#154000
b1111111110111101 -
b1111111111000111 .
b1111111110111110 +
b1111111111001000 )
0(
#155000
1(
#156000
b1111111110111100 -
b1111111111000110 .
b1111111110111101 +
b1111111111000111 )
0(
#157000
1(
#158000
b1111111110111011 -
b1111111111000101 .
b1111111110111100 +
b1111111111000110 )
0(
#159000
1(
#160000
b1111111110111010 -
b1111111111000100 .
b1111111110111011 +
b1111111111000101 )
0(
#161000
1(
#162000
b1111111110111001 -
b1111111111000011 .
b1111111110111010 +
b1111111111000100 )
0(
#163000
1(
#164000
b1111111110111000 -
b1111111111000010 .
b1111111110111001 +
b1111111111000011 )
0(
#165000
1(
#166000
b1111111110110111 -
b1111111111000001 .
b1111111110111000 +
b1111111111000010 )
0(
#167000
1(
#168000
b1111111110110110 -
b1111111111000000 .
b1111111110110111 +
b1111111111000001 )
0(
#169000
1(
#170000
b1111111110110101 -
b1111111110111111 .
b1111111110110110 +
b1111111111000000 )
0(
#171000
1(
#172000
b1111111110110100 -
b1111111110111110 .
b1111111110110101 +
b1111111110111111 )
0(
#173000
1(
#174000
b1111111110110011 -
b1111111110111101 .
b1111111110110100 +
b1111111110111110 )
0(
#175000
1(
#176000
b1111111110110010 -
b1111111110111100 .
b1111111110110011 +
b1111111110111101 )
0(
#177000
1(
#178000
b1111111110110001 -
b1111111110111011 .
b1111111110110010 +
b1111111110111100 )
0(
#179000
1(
#180000
b1111111110110000 -
b1111111110111010 .
b1111111110110001 +
b1111111110111011 )
0(
#181000
1(
#182000
b1111111110101111 -
b1111111110111001 .
b1111111110110000 +
b1111111110111010 )
0(
#183000
1(
#184000
b1111111110101110 -
b1111111110111000 .
b1111111110101111 +
b1111111110111001 )
0(
#185000
1(
#186000
b1111111110101101 -
b1111111110110111 .
b1111111110101110 +
b1111111110111000 )
0(
#187000
1(
#188000
b1111111110101100 -
b1111111110110110 .
b1111111110101101 +
b1111111110110111 )
0(
#189000
1(
#190000
b1111111110101011 -
b1111111110110101 .
b1111111110101100 +
b1111111110110110 )
0(
#191000
1(
#192000
b1111111110101010 -
b1111111110110100 .
b1111111110101011 +
b1111111110110101 )
0(
#193000
1(
#194000
b1111111110101001 -
b1111111110110011 .
b1111111110101010 +
b1111111110110100 )
0(
#195000
1(
#196000
b1111111110101000 -
b1111111110110010 .
b1111111110101001 +
b1111111110110011 )
0(
#197000
1(
#198000
b1111111110100111 -
b1111111110110001 .
b1111111110101000 +
b1111111110110010 )
0(
#199000
1(
#200000
b1111111110100110 -
b1111111110110000 .
b1111111110100111 +
b1111111110110001 )
0(
#201000
1(
#202000
b1111111110100101 -
b1111111110101111 .
b1111111110100110 +
b1111111110110000 )
0(
#203000
1(
#204000
b1111111110100100 -
b1111111110101110 .
b1111111110100101 +
b1111111110101111 )
0(
#205000
1(
#206000
b1111111110100011 -
b1111111110101101 .
b1111111110100100 +
b1111111110101110 )
0(
#207000
1(
#208000
b1111111110100010 -
b1111111110101100 .
b1111111110100011 +
b1111111110101101 )
0(
#209000
1(
#210000
b1111111110100001 -
b1111111110101011 .
b1111111110100010 +
b1111111110101100 )
0(
#211000
1(
#212000
b1111111110100000 -
b1111111110101010 .
b1111111110100001 +
b1111111110101011 )
0(
#213000
1(
#214000
b1111111110011111 -
b1111111110101001 .
b1111111110100000 +
b1111111110101010 )
0(
#215000
1(
#216000
b1111111110011110 -
b1111111110101000 .
b1111111110011111 +
b1111111110101001 )
0(
#217000
1(
#218000
b1111111110011101 -
b1111111110100111 .
b1111111110011110 +
b1111111110101000 )
0(
#219000
1(
#220000
b1111111110011100 -
b1111111110100110 .
b1111111110011101 +
b1111111110100111 )
0(
#221000
1(
#222000
b1111111110011011 -
b1111111110100101 .
b1111111110011100 +
b1111111110100110 )
0(
#223000
1(
#224000
b1111111110011010 -
b1111111110100100 .
b1111111110011011 +
b1111111110100101 )
0(
#225000
1(
#226000
b1111111110011001 -
b1111111110100011 .
b1111111110011010 +
b1111111110100100 )
0(
#227000
1(
#228000
b1111111110011000 -
b1111111110100010 .
b1111111110011001 +
b1111111110100011 )
0(
#229000
1(
#230000
b1111111110010111 -
b1111111110100001 .
b1111111110011000 +
b1111111110100010 )
0(
#231000
1(
#232000
b1111111110010110 -
b1111111110100000 .
b1111111110010111 +
b1111111110100001 )
0(
#233000
1(
#234000
b1111111110010101 -
b1111111110011111 .
b1111111110010110 +
b1111111110100000 )
0(
#235000
1(
#236000
b1111111110010100 -
b1111111110011110 .
b1111111110010101 +
b1111111110011111 )
0(
#237000
1(
#238000
b1111111110010011 -
b1111111110011101 .
b1111111110010100 +
b1111111110011110 )
0(
#239000
1(
#240000
b1111111110010010 -
b1111111110011100 .
b1111111110010011 +
b1111111110011101 )
0(
#241000
1(
#242000
b1111111110010001 -
b1111111110011011 .
b1111111110010010 +
b1111111110011100 )
0(
#243000
1(
#244000
b1111111110010000 -
b1111111110011010 .
b1111111110010001 +
b1111111110011011 )
0(
#245000
1(
#246000
b1111111110001111 -
b1111111110011001 .
b1111111110010000 +
b1111111110011010 )
0(
#247000
1(
#248000
b1111111110001110 -
b1111111110011000 .
b1111111110001111 +
b1111111110011001 )
0(
#249000
1(
#250000
b1111111110001101 -
b1111111110010111 .
b1111111110001110 +
b1111111110011000 )
0(
#251000
1(
#252000
b1111111110001100 -
b1111111110010110 .
b1111111110001101 +
b1111111110010111 )
0(
#253000
1(
#254000
b1111111110001011 -
b1111111110010101 .
b1111111110001100 +
b1111111110010110 )
0(
#255000
1(
#256000
b1111111110001010 -
b1111111110010100 .
b1111111110001011 +
b1111111110010101 )
0(
#257000
1(
#258000
b1111111110001001 -
b1111111110010011 .
b1111111110001010 +
b1111111110010100 )
0(
#259000
1(
#260000
b1111111110001000 -
b1111111110010010 .
b1111111110001001 +
b1111111110010011 )
0(
#261000
1(
#262000
b1111111110000111 -
b1111111110010001 .
b1111111110001000 +
b1111111110010010 )
0(
#263000
1(
#264000
b1111111110000110 -
b1111111110010000 .
b1111111110000111 +
b1111111110010001 )
0(
#265000
1(
#266000
b1111111110000101 -
b1111111110001111 .
b1111111110000110 +
b1111111110010000 )
0(
#267000
1(
#268000
b1111111110000100 -
b1111111110001110 .
b1111111110000101 +
b1111111110001111 )
0(
#269000
1(
#270000
b1111111110000011 -
b1111111110001101 .
b1111111110000100 +
b1111111110001110 )
0(
#271000
1(
#272000
b1111111110000010 -
b1111111110001100 .
b1111111110000011 +
b1111111110001101 )
0(
#273000
1(
#274000
b1111111110000001 -
b1111111110001011 .
b1111111110000010 +
b1111111110001100 )
0(
#275000
1(
#276000
b1111111110000000 -
b1111111110001010 .
b1111111110000001 +
b1111111110001011 )
0(
#277000
1(
#278000
b1111111101111111 -
b1111111110001001 .
b1111111110000000 +
b1111111110001010 )
0(
#279000
1(
#280000
b1111111101111110 -
b1111111110001000 .
b1111111101111111 +
b1111111110001001 )
0(
#281000
1(
#282000
b1111111101111101 -
b1111111110000111 .
b1111111101111110 +
b1111111110001000 )
0(
#283000
1(
#284000
b1111111101111100 -
b1111111110000110 .
b1111111101111101 +
b1111111110000111 )
0(
#285000
1(
#286000
b1111111101111011 -
b1111111110000101 .
b1111111101111100 +
b1111111110000110 )
0(
#287000
1(
#288000
b1111111101111010 -
b1111111110000100 .
b1111111101111011 +
b1111111110000101 )
0(
#289000
1(
#290000
b1111111101111001 -
b1111111110000011 .
b1111111101111010 +
b1111111110000100 )
0(
#291000
1(
#292000
b1111111101111000 -
b1111111110000010 .
b1111111101111001 +
b1111111110000011 )
0(
#293000
1(
#294000
b1111111101110111 -
b1111111110000001 .
b1111111101111000 +
b1111111110000010 )
0(
#295000
1(
#296000
b1111111101110110 -
b1111111110000000 .
b1111111101110111 +
b1111111110000001 )
0(
#297000
1(
#298000
b1111111101110101 -
b1111111101111111 .
b1111111101110110 +
b1111111110000000 )
0(
#299000
1(
#300000
b1111111101110100 -
b1111111101111110 .
b1111111101110101 +
b1111111101111111 )
0(
#301000
1(
#302000
b1111111101110011 -
b1111111101111101 .
b1111111101110100 +
b1111111101111110 )
0(
#303000
1(
#304000
b1111111101110010 -
b1111111101111100 .
b1111111101110011 +
b1111111101111101 )
0(
#305000
1(
#306000
b1111111101110001 -
b1111111101111011 .
b1111111101110010 +
b1111111101111100 )
0(
#307000
1(
#308000
b1111111101110000 -
b1111111101111010 .
b1111111101110001 +
b1111111101111011 )
0(
#309000
1(
#310000
b1111111101101111 -
b1111111101111001 .
b1111111101110000 +
b1111111101111010 )
0(
#311000
1(
#312000
b1111111101101110 -
b1111111101111000 .
b1111111101101111 +
b1111111101111001 )
0(
#313000
1(
#314000
b1111111101101101 -
b1111111101110111 .
b1111111101101110 +
b1111111101111000 )
0(
#315000
1(
#316000
b1111111101101100 -
b1111111101110110 .
b1111111101101101 +
b1111111101110111 )
0(
#317000
1(
#318000
b1111111101101011 -
b1111111101110101 .
b1111111101101100 +
b1111111101110110 )
0(
#319000
1(
#320000
b1111111101101010 -
b1111111101110100 .
b1111111101101011 +
b1111111101110101 )
0(
#321000
1(
#322000
b1111111101101001 -
b1111111101110011 .
b1111111101101010 +
b1111111101110100 )
0(
#323000
1(
#324000
b1111111101101000 -
b1111111101110010 .
b1111111101101001 +
b1111111101110011 )
0(
#325000
1(
#326000
b1111111101100111 -
b1111111101110001 .
b1111111101101000 +
b1111111101110010 )
0(
#327000
1(
#328000
b1111111101100110 -
b1111111101110000 .
b1111111101100111 +
b1111111101110001 )
0(
#329000
1(
#330000
b1111111101100101 -
b1111111101101111 .
b1111111101100110 +
b1111111101110000 )
0(
#331000
1(
#332000
b1111111101100100 -
b1111111101101110 .
b1111111101100101 +
b1111111101101111 )
0(
#333000
1(
#334000
b1111111101100011 -
b1111111101101101 .
b1111111101100100 +
b1111111101101110 )
0(
#335000
1(
#336000
b1111111101100010 -
b1111111101101100 .
b1111111101100011 +
b1111111101101101 )
0(
#337000
1(
#338000
b1111111101100001 -
b1111111101101011 .
b1111111101100010 +
b1111111101101100 )
0(
#339000
1(
#340000
b1111111101100000 -
b1111111101101010 .
b1111111101100001 +
b1111111101101011 )
0(
#341000
1(
#342000
b1111111101011111 -
b1111111101101001 .
b1111111101100000 +
b1111111101101010 )
0(
#343000
1(
#344000
b1111111101011110 -
b1111111101101000 .
b1111111101011111 +
b1111111101101001 )
0(
#345000
1(
#346000
b1111111101011101 -
b1111111101100111 .
b1111111101011110 +
b1111111101101000 )
0(
#347000
1(
#348000
b1111111101011100 -
b1111111101100110 .
b1111111101011101 +
b1111111101100111 )
0(
#349000
1(
#350000
b1111111101011011 -
b1111111101100101 .
b1111111101011100 +
b1111111101100110 )
0(
#351000
1(
#352000
b1111111101011010 -
b1111111101100100 .
b1111111101011011 +
b1111111101100101 )
0(
#353000
1(
#354000
b1111111101011001 -
b1111111101100011 .
b1111111101011010 +
b1111111101100100 )
0(
#355000
1(
#356000
b1111111101011000 -
b1111111101100010 .
b1111111101011001 +
b1111111101100011 )
0(
#357000
1(
#358000
b1111111101010111 -
b1111111101100001 .
b1111111101011000 +
b1111111101100010 )
0(
#359000
1(
#360000
b1111111101010110 -
b1111111101100000 .
b1111111101010111 +
b1111111101100001 )
0(
#361000
1(
#362000
b1111111101010101 -
b1111111101011111 .
b1111111101010110 +
b1111111101100000 )
0(
#363000
1(
#364000
b1111111101010100 -
b1111111101011110 .
b1111111101010101 +
b1111111101011111 )
0(
#365000
1(
#366000
b1111111101010011 -
b1111111101011101 .
b1111111101010100 +
b1111111101011110 )
0(
#367000
1(
#368000
b1111111101010010 -
b1111111101011100 .
b1111111101010011 +
b1111111101011101 )
0(
#369000
1(
#370000
b1111111101010001 -
b1111111101011011 .
b1111111101010010 +
b1111111101011100 )
0(
#371000
1(
#372000
b1111111101010000 -
b1111111101011010 .
b1111111101010001 +
b1111111101011011 )
0(
#373000
1(
#374000
b1111111101001111 -
b1111111101011001 .
b1111111101010000 +
b1111111101011010 )
0(
#375000
1(
#376000
b1111111101001110 -
b1111111101011000 .
b1111111101001111 +
b1111111101011001 )
0(
#377000
1(
#378000
b1111111101001101 -
b1111111101010111 .
b1111111101001110 +
b1111111101011000 )
0(
#379000
1(
#380000
b1111111101001100 -
b1111111101010110 .
b1111111101001101 +
b1111111101010111 )
0(
#381000
1(
#382000
b1111111101001011 -
b1111111101010101 .
b1111111101001100 +
b1111111101010110 )
0(
#383000
1(
#384000
b1111111101001010 -
b1111111101010100 .
b1111111101001011 +
b1111111101010101 )
0(
#385000
1(
#386000
b1111111101001001 -
b1111111101010011 .
b1111111101001010 +
b1111111101010100 )
0(
#387000
1(
#388000
b1111111101001000 -
b1111111101010010 .
b1111111101001001 +
b1111111101010011 )
0(
#389000
1(
#390000
b1111111101000111 -
b1111111101010001 .
b1111111101001000 +
b1111111101010010 )
0(
#391000
1(
#392000
b1111111101000110 -
b1111111101010000 .
b1111111101000111 +
b1111111101010001 )
0(
#393000
1(
#394000
b1111111101000101 -
b1111111101001111 .
b1111111101000110 +
b1111111101010000 )
0(
#395000
1(
#396000
b1111111101000100 -
b1111111101001110 .
b1111111101000101 +
b1111111101001111 )
0(
#397000
1(
#398000
b1111111101000011 -
b1111111101001101 .
b1111111101000100 +
b1111111101001110 )
0(
#399000
1(
#400000
b1111111101000010 -
b1111111101001100 .
b1111111101000011 +
b1111111101001101 )
0(
#401000
1(
#402000
b1111111101000001 -
b1111111101001011 .
b1111111101000010 +
b1111111101001100 )
0(
#403000
1(
#404000
b1111111101000000 -
b1111111101001010 .
b1111111101000001 +
b1111111101001011 )
0(
#405000
1(
#406000
b1111111100111111 -
b1111111101001001 .
b1111111101000000 +
b1111111101001010 )
0(
#407000
1(
#408000
b1111111100111110 -
b1111111101001000 .
b1111111100111111 +
b1111111101001001 )
0(
#409000
1(
#410000
b1111111100111101 -
b1111111101000111 .
b1111111100111110 +
b1111111101001000 )
0(
#411000
1(
#412000
b1111111100111100 -
b1111111101000110 .
b1111111100111101 +
b1111111101000111 )
0(
#413000
1(
#414000
b1111111100111011 -
b1111111101000101 .
b1111111100111100 +
b1111111101000110 )
0(
#415000
1(
#416000
b1111111100111010 -
b1111111101000100 .
b1111111100111011 +
b1111111101000101 )
0(
#417000
1(
#418000
b1111111100111001 -
b1111111101000011 .
b1111111100111010 +
b1111111101000100 )
0(
#419000
1(
#420000
b1111111100111000 -
b1111111101000010 .
b1111111100111001 +
b1111111101000011 )
0(
#421000
1(
#422000
b1111111100110111 -
b1111111101000001 .
b1111111100111000 +
b1111111101000010 )
0(
#423000
1(
#424000
b1111111100110110 -
b1111111101000000 .
b1111111100110111 +
b1111111101000001 )
0(
#425000
1(
#426000
b1111111100110101 -
b1111111100111111 .
b1111111100110110 +
b1111111101000000 )
0(
#427000
1(
#428000
b1111111100110100 -
b1111111100111110 .
b1111111100110101 +
b1111111100111111 )
0(
#429000
1(
#430000
b1111111100110011 -
b1111111100111101 .
b1111111100110100 +
b1111111100111110 )
0(
#431000
1(
#432000
b1111111100110010 -
b1111111100111100 .
b1111111100110011 +
b1111111100111101 )
0(
