src/math/math.v

module math(rst, clk, a, b, c, d, result);

	input rst;
	input clk;
	input wire [15:0] a;
	input wire [15:0] b;
	input wire [15:0] c;
	input wire [15:0] d;
	output reg [15:0] result;

	reg [32:0] ab;
	reg [32:0] cd;
	
	
	always @(posedge clk) begin
		ab <= a*b;
		cd <= c*d;
		result <= ab + cd;
	end
		

endmodule

src/math/sim_math.v

`timescale 1 ns / 1 ps

module sim_math;

	reg clk;
	reg rst;
	reg i;
	reg [15:0] a;
	reg [15:0] b;
	reg [15:0] c;
	reg [15:0] d;
	wire [15:0] result;
	
	math m (rst, clk, a, b, c, d, result);
	
	initial begin
		$dumpfile("math.vcd");
		$dumpvars(2, m);
		
		clk <= 0;
		rst <= 1;

		a <= 0;
		b <= 0;
		c <= 0;
		d <= 0;

		#4 rst <= 0;		
		
		a <= 10;
		b <= 11;
		c <= 12;
		d <= 13;

		#2 rst <= 0;		
		
		a <= 20;
		b <= 21;
		c <= 22;
		d <= 23;
	end

	always #1 clk = ~clk;
	
	always #1000 $finish;   
	        
	        
endmodule

src/math/math.vcd
$date
    Tue Apr  5 08:57:40 2005
$end
$version
    GPLCVER_2.10b of 02/03/05
$end
$timescale
    1 ps
$end
$scope module sim_math $end
$scope module m $end
$var wire      16 !    a [15:0] $end
$var reg      33 "    ab [32:0] $end
$var wire      16 #    b [15:0] $end
$var wire      16 $    c [15:0] $end
$var reg      33 %    cd [32:0] $end
$var wire       1 &    clk $end
$var wire      16 '    d [15:0] $end
$var reg      16 (    result [15:0] $end
$var wire       1 )    rst $end
$upscope $end
$upscope $end
$enddefinitions $end
#0
$dumpvars
b0 !
bx "
b0 #
b0 $
bx %
0&
b0 '
bx (
1)
$end
#1000
b0 %
b0 "
1&
#2000
0&
#3000
b0 (
1&
#4000
b1101 '
b1100 $
b1011 #
b1010 !
0)
0&
#5000
b10011100 %
b1101110 "
1&
#6000
b10111 '
b10110 $
b10101 #
b10100 !
0&
#7000
b100001010 (
b111111010 %
b110100100 "
1&
#8000
0&
#9000
b1110011110 (
1&
